{
  "android": {
      "olddebug": {
          "keystore": "../android/mwxing_debug.keystore",
          "storePassword": "Xj123456*",
          "alias": "mwxing_debug.keystore",
          "password" : "Xj123456*",
          "keystoreType": "JKS"
      },
      "debug": {
        "keystore": "../android/mwxing-release.keystore",
        "storePassword": "MWXing1234*",
        "alias": "mwxing-release",
        "password" : "MWXing1234*",
        "keystoreType": "JKS"
      },
      "release": {
          "keystore": "../android/mwxing-release.keystore",
          "storePassword": "MWXing1234*",
          "alias": "mwxing-release",
          "password" : "MWXing1234*",
          "keystoreType": "JKS"
      }
  },
  "ios": {
    "debug": {
      "codeSignIdentity": "iPhone Distribution: Jinyang Zhang (D5A8L43W8A)",
      "provisioningProfile": "202650d3-3ae6-48ab-91e4-78740920a00b",
      "packageType": "ad-hoc",
      "automaticProvisioning": true,
      "buildFlag": [
          "EMBEDDED_CONTENT_CONTAINS_SWIFT = YES",
          "ALWAYS_EMBED_SWIFT_STANDARD_LIBRARIES=YES",
          "LD_RUNPATH_SEARCH_PATHS = \"@executable_path/Frameworks\""
      ]
    },
    "release": {
      "codeSignIdentity": "iPhone Distribution: Jinyang Zhang (D5A8L43W8A)",
      "provisioningProfile": "a87d5d47-5417-4cb7-8fbc-46835d7d9494",
      "packageType": "app-store",
      "developmentTeam": "D5A8L43W8A",
      "automaticProvisioning": true,
      "buildFlag": [
          "EMBEDDED_CONTENT_CONTAINS_SWIFT = YES",
          "ALWAYS_EMBED_SWIFT_STANDARD_LIBRARIES = YES",
          "LD_RUNPATH_SEARCH_PATHS = \"@executable_path/Frameworks\""
      ]
    }
  }
}
